{
    "version": "2022.07.1-03c83c8",
    "description": "An easy to use N64 emulator",
    "license": "GPL-3.0",
    "homepage": "https://m64p.github.io/",
    "extract_dir": "mupen64plus",
    "architecture": {
        "64bit": {
            "url": "https://github.com/loganmc10/m64p/releases/download/v2022.07.1/m64p-win64-03c83c8.zip",
            "hash": "48a642d4b1161ed185135932f6d10c7c2b4f25579dc5591daa17e6de519924d2"
        }
    },
    "shortcuts": [
        [
            "mupen64plus-gui.exe",
            "m64p"
        ]
    ],
    "checkver": {
        "url": "https://github.com/loganmc10/m64p/releases/latest",
        "regex": "(?<date>\\d{4}\\.\\d{1,2}\\.\\d{1,2})((.|\\n)*)win64-(?<commit>\\w{7})\\.zip",
        "replace": "${date}-${commit}"
    },
    "autoupdate": {
        "architecture": {
            "64bit": {
                "url": "https://github.com/loganmc10/m64p/releases/download/v$matchDate/m64p-win64-$matchCommit.zip"
            }
        }
    }
}
